escode.cpython-37m-darwin.so
escode-3.0.1.dist-info/METADATA
escode-3.0.1.dist-info/WHEEL
escode-3.0.1.dist-info/entry_points.txt
escode-3.0.1.dist-info/RECORD