Metadata-Version: 2.1
Name: escode
Version: 3.0.1
Summary: ESCODE binary serialization
License: MIT
Author: Akhil Wable
Author-email: akhil.wable@gmail.com
Classifier: Programming Language :: Python :: 2.7
Classifier: Programming Language :: Python :: 3
Classifier: Programming Language :: Python :: Implementation :: CPython
Classifier: Programming Language :: C
Home-Page: https://github.com/awable/escode
Requires-Dist: six
